hedonic/Game.py
hedonic/__init__.py
hedonic/py.typed
hedonic/utils.py
hedonic-0.0.10.dist-info/WHEEL
hedonic-0.0.10.dist-info/METADATA
hedonic-0.0.10.dist-info/RECORD
