Metadata-Version: 2.3
Name: hedonic
Version: 0.0.10
Summary: A Python library for hedonic games
Author: Lucas Lopes Felipe
Requires-Dist: lucas-igraph
Requires-Dist: numpy
Requires-Python: >=3.12
